LICENSE
README.md
setup.cfg
setup.py
kfp_tekton_server_api/__init__.py
kfp_tekton_server_api/api_client.py
kfp_tekton_server_api/configuration.py
kfp_tekton_server_api/exceptions.py
kfp_tekton_server_api/rest.py
kfp_tekton_server_api.egg-info/PKG-INFO
kfp_tekton_server_api.egg-info/SOURCES.txt
kfp_tekton_server_api.egg-info/dependency_links.txt
kfp_tekton_server_api.egg-info/requires.txt
kfp_tekton_server_api.egg-info/top_level.txt
kfp_tekton_server_api/api/__init__.py
kfp_tekton_server_api/api/experiment_service_api.py
kfp_tekton_server_api/api/healthz_service_api.py
kfp_tekton_server_api/api/job_service_api.py
kfp_tekton_server_api/api/pipeline_service_api.py
kfp_tekton_server_api/api/pipeline_upload_service_api.py
kfp_tekton_server_api/api/run_service_api.py
kfp_tekton_server_api/models/__init__.py
kfp_tekton_server_api/models/job_mode.py
kfp_tekton_server_api/models/pipeline_spec_runtime_config.py
kfp_tekton_server_api/models/protobuf_any.py
kfp_tekton_server_api/models/report_run_metrics_response_report_run_metric_result.py
kfp_tekton_server_api/models/report_run_metrics_response_report_run_metric_result_status.py
kfp_tekton_server_api/models/run_metric_format.py
kfp_tekton_server_api/models/v1_cron_schedule.py
kfp_tekton_server_api/models/v1_experiment.py
kfp_tekton_server_api/models/v1_experiment_storage_state.py
kfp_tekton_server_api/models/v1_get_healthz_response.py
kfp_tekton_server_api/models/v1_get_template_response.py
kfp_tekton_server_api/models/v1_job.py
kfp_tekton_server_api/models/v1_list_experiments_response.py
kfp_tekton_server_api/models/v1_list_jobs_response.py
kfp_tekton_server_api/models/v1_list_pipeline_versions_response.py
kfp_tekton_server_api/models/v1_list_pipelines_response.py
kfp_tekton_server_api/models/v1_list_runs_response.py
kfp_tekton_server_api/models/v1_parameter.py
kfp_tekton_server_api/models/v1_periodic_schedule.py
kfp_tekton_server_api/models/v1_pipeline.py
kfp_tekton_server_api/models/v1_pipeline_runtime.py
kfp_tekton_server_api/models/v1_pipeline_spec.py
kfp_tekton_server_api/models/v1_pipeline_version.py
kfp_tekton_server_api/models/v1_read_artifact_response.py
kfp_tekton_server_api/models/v1_relationship.py
