Metadata-Version: 2.1
Name: kfp-tekton-server-api
Version: 1.5.0
Summary: Kubeflow Pipelines on Tekton API
Home-page: https://github.com/kubeflow/kfp-tekton
Author: kfp-tekton
Author-email: prashsh1@in.ibm.com
License: Apache 2.0
Keywords: OpenAPI,OpenAPI-Generator,Kubeflow Pipelines on Tekton API
License-File: LICENSE
